international_address_formatter/__init__.py
international_address_formatter/format.py
international_address_formatter/data/worldwide.yml
international_address_formatter-1.0.2.dist-info/LICENSE.txt
international_address_formatter-1.0.2.dist-info/METADATA
international_address_formatter-1.0.2.dist-info/WHEEL
international_address_formatter-1.0.2.dist-info/top_level.txt
international_address_formatter-1.0.2.dist-info/RECORD
