Metadata-Version: 2.1
Name: international-address-formatter
Version: 1.0.2
Summary: International address formatter
Home-page: https://github.com/dunkelstern/international_address_formatter
Author: Johannes Schriewer
Author-email: hallo@dunkelstern.de
License: LICENSE.txt
Keywords: address formatting,international
Platform: UNKNOWN
Classifier: Development Status :: 5 - Production/Stable
Classifier: Intended Audience :: Developers
Classifier: License :: OSI Approved :: BSD License
Classifier: Programming Language :: Python
Classifier: Programming Language :: Python :: 3
Classifier: Programming Language :: Python :: 3.5
Classifier: Programming Language :: Python :: 3.6
Classifier: Programming Language :: Python :: 3.7
Classifier: Operating System :: OS Independent
Requires-Dist: PyYAML (>=5.0)
Requires-Dist: pystache (>=0.5)
